{
  "Appalachian": {
    "count": 256,
    "status": "ok"
  },
  "Cal Ripken": {
    "count": 302,
    "status": "ok"
  },
  "Cape Cod": {
    "count": 298,
    "status": "ok"
  },
  "Coastal Plain": {
    "count": 514,
    "status": "ok"
  },
  "FCBL": {
    "count": 361,
    "status": "ok"
  },
  "MLB Draft": {
    "count": 268,
    "status": "ok"
  },
  "NECBL": {
    "count": 575,
    "status": "ok"
  },
  "Northwoods": {
    "count": 0,
    "status": "failed"
  },
  "PGCBL": {
    "count": 0,
    "status": "ok"
  },
  "Prospect": {
    "count": 815,
    "status": "ok"
  }
}