{
  "2026-06-30|Aaron Watson:entered": true,
  "2026-06-30|Aaron Watson:entered:ts": "2026-06-30T01:16:41.782347+00:00",
  "2026-06-29|Garrett Whitlock:entered": true,
  "2026-06-29|Garrett Whitlock:entered:ts": "2026-06-30T01:46:40.703652+00:00",
  "2026-06-29|Garrett Whitlock:standout_recap": true,
  "2026-06-29|Garrett Whitlock:standout_recap:ts": "2026-06-30T01:46:40.989815+00:00",
  "2026-06-30|Tanner Gordon:promo_115": true,
  "2026-06-30|Tanner Gordon:promo_115:ts": "2026-06-30T22:05:44.678330+00:00",
  "2026-06-30|Cade Doughty:hr": 1,
  "2026-06-30|Cade Doughty:hr:ts": "2026-07-01T00:16:46.689546+00:00",
  "2026-07-01|Tanner Gordon:entered": true,
  "2026-07-01|Tanner Gordon:entered:ts": "2026-07-01T01:01:54.171569+00:00",
  "2026-07-01|David Hagaman:entered": true,
  "2026-07-01|David Hagaman:entered:ts": "2026-07-01T01:46:44.372597+00:00",
  "2026-06-30|Cade Doughty:standout_recap": true,
  "2026-06-30|Cade Doughty:standout_recap:ts": "2026-07-01T01:46:44.666500+00:00",
  "2026-06-30|Justin Riemer:3ob": true,
  "2026-06-30|Justin Riemer:3ob:ts": "2026-07-01T02:04:03.429062+00:00",
  "2026-07-01|David Hagaman:ks": 9,
  "2026-07-01|David Hagaman:ks:ts": "2026-07-01T03:16:52.471525+00:00",
  "2026-07-01|David Hagaman:qs": true,
  "2026-07-01|David Hagaman:qs:ts": "2026-07-01T02:47:01.778472+00:00",
  "2026-06-30|Sterlin Thompson:hr": 1,
  "2026-06-30|Sterlin Thompson:hr:ts": "2026-07-01T02:47:04.154809+00:00",
  "2026-07-01|Kade Brown:entered": true,
  "2026-07-01|Kade Brown:entered:ts": "2026-07-01T03:32:06.059494+00:00"
}