[
  {
    "player_name": "Austin Amaral",
    "team": "Washington Nationals",
    "level": "Pro",
    "is_client": true,
    "tags": {
      "position": "Pitcher",
      "draft_class": "N/A",
      "roster_priority": 3
    },
    "window": "7d",
    "window_grade": "— Insufficient",
    "stats": {
      "ip": "--",
      "k": "--",
      "bb": "--",
      "era": "--",
      "whip": "--",
      "k_per_9": "--",
      "bb_per_9": "--",
      "k_pct": "--",
      "bb_pct": "--"
    },
    "games_played": 0,
    "last_updated": "2026-03-08T11:15:50.902552Z"
  },
  {
    "player_name": "Brennan Orf",
    "team": "Toronto Blue Jays",
    "level": "Pro",
    "is_client": true,
    "tags": {
      "position": "Hitter",
      "draft_class": "N/A",
      "roster_priority": 4
    },
    "window": "7d",
    "window_grade": "— Insufficient",
    "stats": {
      "pa": "--",
      "ab": "--",
      "h": "--",
      "hr": "--",
      "rbi": "--",
      "r": "--",
      "sb": "--",
      "avg": "--",
      "obp": "--",
      "slg": "--",
      "ops": "--",
      "k_pct": "--",
      "bb_pct": "--"
    },
    "games_played": 0,
    "last_updated": "2026-03-08T11:15:50.914906Z"
  },
  {
    "player_name": "Blake Rambusch",
    "team": "Seattle Mariners",
    "level": "Pro",
    "is_client": true,
    "tags": {
      "position": "Hitter",
      "draft_class": "N/A",
      "roster_priority": 3
    },
    "window": "7d",
    "window_grade": "🥶 Cold",
    "stats": {
      "pa": 7,
      "ab": 6,
      "h": 0,
      "hr": 0,
      "rbi": 0,
      "r": 1,
      "sb": 0,
      "avg": ".000",
      "obp": ".143",
      "slg": ".000",
      "ops": ".143",
      "k_pct": "28.6%",
      "bb_pct": "14.3%"
    },
    "games_played": 5,
    "last_updated": "2026-03-08T11:15:50.940785Z",
    "game_log": [
      {
        "date": "2026-03-07",
        "opponent": "vs ",
        "stats": {
          "h": 0,
          "ab": 1,
          "hr": 0,
          "rbi": 0,
          "r": 0,
          "bb": 0,
          "k": 1,
          "sb": 0
        }
      },
      {
        "date": "2026-03-06",
        "opponent": "",
        "stats": {
          "h": 0,
          "ab": 1,
          "hr": 0,
          "rbi": 0,
          "r": 0,
          "bb": 0,
          "k": 0,
          "sb": 0
        }
      },
      {
        "date": "2026-03-05",
        "opponent": "vs ",
        "stats": {
          "h": 0,
          "ab": 2,
          "hr": 0,
          "rbi": 0,
          "r": 0,
          "bb": 0,
          "k": 1,
          "sb": 0
        }
      },
      {
        "date": "2026-03-04",
        "opponent": "",
        "stats": {
          "h": 0,
          "ab": 0,
          "hr": 0,
          "rbi": 0,
          "r": 0,
          "bb": 0,
          "k": 0,
          "sb": 0
        }
      },
      {
        "date": "2026-03-01",
        "opponent": "vs ",
        "stats": {
          "h": 0,
          "ab": 2,
          "hr": 0,
          "rbi": 0,
          "r": 1,
          "bb": 1,
          "k": 0,
          "sb": 0
        }
      }
    ]
  },
  {
    "player_name": "Aaron Watson",
    "team": "Cincinnati Reds",
    "level": "Pro",
    "is_client": true,
    "tags": {
      "position": "Pitcher",
      "draft_class": "N/A",
      "roster_priority": 2
    },
    "window": "7d",
    "window_grade": "— Insufficient",
    "stats": {
      "ip": "--",
      "k": "--",
      "bb": "--",
      "era": "--",
      "whip": "--",
      "k_per_9": "--",
      "bb_per_9": "--",
      "k_pct": "--",
      "bb_pct": "--"
    },
    "games_played": 0,
    "last_updated": "2026-03-08T11:15:50.929599Z"
  },
  {
    "player_name": "Cade Doughty",
    "team": "Toronto Blue Jays",
    "level": "Pro",
    "is_client": true,
    "tags": {
      "position": "Hitter",
      "draft_class": "N/A",
      "roster_priority": 2
    },
    "window": "7d",
    "window_grade": "— Insufficient",
    "stats": {
      "pa": "--",
      "ab": "--",
      "h": "--",
      "hr": "--",
      "rbi": "--",
      "r": "--",
      "sb": "--",
      "avg": "--",
      "obp": "--",
      "slg": "--",
      "ops": "--",
      "k_pct": "--",
      "bb_pct": "--"
    },
    "games_played": 0,
    "last_updated": "2026-03-08T11:15:51.446814Z"
  },
  {
    "player_name": "Davis Sharpe",
    "team": "Cleveland Guardians",
    "level": "Pro",
    "is_client": true,
    "tags": {
      "position": "Pitcher",
      "draft_class": "N/A",
      "roster_priority": 3
    },
    "window": "7d",
    "window_grade": "— Insufficient",
    "stats": {
      "ip": "--",
      "k": "--",
      "bb": "--",
      "era": "--",
      "whip": "--",
      "k_per_9": "--",
      "bb_per_9": "--",
      "k_pct": "--",
      "bb_pct": "--"
    },
    "games_played": 0,
    "last_updated": "2026-03-08T11:15:51.479456Z"
  },
  {
    "player_name": "Carter Johnson",
    "team": "Miami Marlins",
    "level": "Pro",
    "is_client": true,
    "tags": {
      "position": "Hitter",
      "draft_class": "N/A",
      "roster_priority": 2
    },
    "window": "7d",
    "window_grade": "— Insufficient",
    "stats": {
      "pa": "--",
      "ab": "--",
      "h": "--",
      "hr": "--",
      "rbi": "--",
      "r": "--",
      "sb": "--",
      "avg": "--",
      "obp": "--",
      "slg": "--",
      "ops": "--",
      "k_pct": "--",
      "bb_pct": "--"
    },
    "games_played": 0,
    "last_updated": "2026-03-08T11:15:51.498374Z"
  },
  {
    "player_name": "Dax Kilby",
    "team": "New York Yankees",
    "level": "Pro",
    "is_client": true,
    "tags": {
      "position": "Hitter",
      "draft_class": "N/A",
      "roster_priority": 1
    },
    "window": "7d",
    "window_grade": "— Insufficient",
    "stats": {
      "pa": "--",
      "ab": "--",
      "h": "--",
      "hr": "--",
      "rbi": "--",
      "r": "--",
      "sb": "--",
      "avg": "--",
      "obp": "--",
      "slg": "--",
      "ops": "--",
      "k_pct": "--",
      "bb_pct": "--"
    },
    "games_played": 0,
    "last_updated": "2026-03-08T11:15:51.503070Z"
  },
  {
    "player_name": "Garrett Whitlock",
    "team": "Boston Red Sox",
    "level": "Pro",
    "is_client": true,
    "tags": {
      "position": "Pitcher",
      "draft_class": "N/A",
      "roster_priority": 1
    },
    "window": "7d",
    "window_grade": "— Insufficient",
    "stats": {
      "ip": "--",
      "k": "--",
      "bb": "--",
      "era": "--",
      "whip": "--",
      "k_per_9": "--",
      "bb_per_9": "--",
      "k_pct": "--",
      "bb_pct": "--"
    },
    "games_played": 0,
    "last_updated": "2026-03-08T11:15:51.985998Z"
  },
  {
    "player_name": "Forrest Wall",
    "team": "Unsigned",
    "level": "Pro",
    "is_client": true,
    "tags": {
      "position": "Hitter",
      "draft_class": "N/A",
      "roster_priority": 3
    },
    "window": "7d",
    "window_grade": "— Insufficient",
    "stats": {
      "pa": "--",
      "ab": "--",
      "h": "--",
      "hr": "--",
      "rbi": "--",
      "r": "--",
      "sb": "--",
      "avg": "--",
      "obp": "--",
      "slg": "--",
      "ops": "--",
      "k_pct": "--",
      "bb_pct": "--"
    },
    "games_played": 0,
    "last_updated": "2026-03-08T11:15:51.911833Z"
  },
  {
    "player_name": "Jack Cebert",
    "team": "New York Yankees",
    "level": "Pro",
    "is_client": true,
    "tags": {
      "position": "Pitcher",
      "draft_class": "N/A",
      "roster_priority": 2
    },
    "window": "7d",
    "window_grade": "— Insufficient",
    "stats": {
      "ip": "--",
      "k": "--",
      "bb": "--",
      "era": "--",
      "whip": "--",
      "k_per_9": "--",
      "bb_per_9": "--",
      "k_pct": "--",
      "bb_pct": "--"
    },
    "games_played": 0,
    "last_updated": "2026-03-08T11:15:51.994109Z"
  },
  {
    "player_name": "Jake Munroe",
    "team": "Los Angeles Angels",
    "level": "Pro",
    "is_client": true,
    "tags": {
      "position": "Hitter",
      "draft_class": "N/A",
      "roster_priority": 3
    },
    "window": "7d",
    "window_grade": "— Insufficient",
    "stats": {
      "pa": "--",
      "ab": "--",
      "h": "--",
      "hr": "--",
      "rbi": "--",
      "r": "--",
      "sb": "--",
      "avg": "--",
      "obp": "--",
      "slg": "--",
      "ops": "--",
      "k_pct": "--",
      "bb_pct": "--"
    },
    "games_played": 2,
    "last_updated": "2026-03-08T11:15:52.017948Z",
    "game_log": [
      {
        "date": "2026-03-07",
        "opponent": "vs ",
        "stats": {
          "h": 0,
          "ab": 1,
          "hr": 0,
          "rbi": 0,
          "r": 0,
          "bb": 1,
          "k": 1,
          "sb": 0
        }
      },
      {
        "date": "2026-03-06",
        "opponent": "",
        "stats": {
          "h": 0,
          "ab": 0,
          "hr": 0,
          "rbi": 0,
          "r": 0,
          "bb": 0,
          "k": 0,
          "sb": 0
        }
      }
    ]
  },
  {
    "player_name": "Justin Riemer",
    "team": "Athletics",
    "level": "Pro",
    "is_client": true,
    "tags": {
      "position": "Hitter",
      "draft_class": "N/A",
      "roster_priority": 3
    },
    "window": "7d",
    "window_grade": "— Insufficient",
    "stats": {
      "pa": "--",
      "ab": "--",
      "h": "--",
      "hr": "--",
      "rbi": "--",
      "r": "--",
      "sb": "--",
      "avg": "--",
      "obp": "--",
      "slg": "--",
      "ops": "--",
      "k_pct": "--",
      "bb_pct": "--"
    },
    "games_played": 0,
    "last_updated": "2026-03-08T11:15:52.316535Z"
  },
  {
    "player_name": "Kade Brown",
    "team": "Athletics",
    "level": "Pro",
    "is_client": true,
    "tags": {
      "position": "Pitcher",
      "draft_class": "N/A",
      "roster_priority": 3
    },
    "window": "7d",
    "window_grade": "— Insufficient",
    "stats": {
      "ip": "--",
      "k": "--",
      "bb": "--",
      "era": "--",
      "whip": "--",
      "k_per_9": "--",
      "bb_per_9": "--",
      "k_pct": "--",
      "bb_pct": "--"
    },
    "games_played": 0,
    "last_updated": "2026-03-08T11:15:52.405576Z"
  },
  {
    "player_name": "Kellon Lindsey",
    "team": "Los Angeles Dodgers",
    "level": "Pro",
    "is_client": true,
    "tags": {
      "position": "Hitter",
      "draft_class": "N/A",
      "roster_priority": 1
    },
    "window": "7d",
    "window_grade": "— Insufficient",
    "stats": {
      "pa": "--",
      "ab": "--",
      "h": "--",
      "hr": "--",
      "rbi": "--",
      "r": "--",
      "sb": "--",
      "avg": "--",
      "obp": "--",
      "slg": "--",
      "ops": "--",
      "k_pct": "--",
      "bb_pct": "--"
    },
    "games_played": 0,
    "last_updated": "2026-03-08T11:15:52.440710Z"
  },
  {
    "player_name": "Michael Dattalo",
    "team": "St. Louis Cardinals",
    "level": "Pro",
    "is_client": true,
    "tags": {
      "position": "Hitter",
      "draft_class": "N/A",
      "roster_priority": 3
    },
    "window": "7d",
    "window_grade": "— Insufficient",
    "stats": {
      "pa": "--",
      "ab": "--",
      "h": "--",
      "hr": "--",
      "rbi": "--",
      "r": "--",
      "sb": "--",
      "avg": "--",
      "obp": "--",
      "slg": "--",
      "ops": "--",
      "k_pct": "--",
      "bb_pct": "--"
    },
    "games_played": 1,
    "last_updated": "2026-03-08T11:15:52.530766Z",
    "game_log": [
      {
        "date": "2026-03-07",
        "opponent": "vs ",
        "stats": {
          "h": 0,
          "ab": 0,
          "hr": 0,
          "rbi": 0,
          "r": 0,
          "bb": 0,
          "k": 0,
          "sb": 0
        }
      }
    ]
  },
  {
    "player_name": "Sterlin Thompson",
    "team": "Colorado Rockies",
    "level": "Pro",
    "is_client": true,
    "tags": {
      "position": "Hitter",
      "draft_class": "N/A",
      "roster_priority": 2
    },
    "window": "7d",
    "window_grade": "🥶 Cold",
    "stats": {
      "pa": 8,
      "ab": 6,
      "h": 0,
      "hr": 0,
      "rbi": 0,
      "r": 0,
      "sb": 0,
      "avg": ".000",
      "obp": ".250",
      "slg": ".000",
      "ops": ".250",
      "k_pct": "50.0%",
      "bb_pct": "25.0%"
    },
    "games_played": 4,
    "last_updated": "2026-03-08T11:15:53.022085Z",
    "game_log": [
      {
        "date": "2026-03-07",
        "opponent": "",
        "stats": {
          "h": 0,
          "ab": 2,
          "hr": 0,
          "rbi": 0,
          "r": 0,
          "bb": 0,
          "k": 1,
          "sb": 0
        }
      },
      {
        "date": "2026-03-06",
        "opponent": "",
        "stats": {
          "h": 0,
          "ab": 1,
          "hr": 0,
          "rbi": 0,
          "r": 0,
          "bb": 1,
          "k": 1,
          "sb": 0
        }
      },
      {
        "date": "2026-03-05",
        "opponent": "vs ",
        "stats": {
          "h": 0,
          "ab": 3,
          "hr": 0,
          "rbi": 0,
          "r": 0,
          "bb": 0,
          "k": 2,
          "sb": 0
        }
      },
      {
        "date": "2026-03-01",
        "opponent": "",
        "stats": {
          "h": 0,
          "ab": 0,
          "hr": 0,
          "rbi": 0,
          "r": 0,
          "bb": 1,
          "k": 0,
          "sb": 0
        }
      }
    ]
  },
  {
    "player_name": "Najer Victor",
    "team": "Los Angeles Angels",
    "level": "Pro",
    "is_client": true,
    "tags": {
      "position": "Pitcher",
      "draft_class": "N/A",
      "roster_priority": 3
    },
    "window": "7d",
    "window_grade": "— Insufficient",
    "stats": {
      "ip": "--",
      "k": "--",
      "bb": "--",
      "era": "--",
      "whip": "--",
      "k_per_9": "--",
      "bb_per_9": "--",
      "k_pct": "--",
      "bb_pct": "--"
    },
    "games_played": 0,
    "last_updated": "2026-03-08T11:15:52.843388Z"
  },
  {
    "player_name": "Ryan DeSanto",
    "team": "Cleveland Guardians",
    "level": "Pro",
    "is_client": true,
    "tags": {
      "position": "Pitcher",
      "draft_class": "N/A",
      "roster_priority": 3
    },
    "window": "7d",
    "window_grade": "— Insufficient",
    "stats": {
      "ip": "--",
      "k": "--",
      "bb": "--",
      "era": "--",
      "whip": "--",
      "k_per_9": "--",
      "bb_per_9": "--",
      "k_pct": "--",
      "bb_pct": "--"
    },
    "games_played": 0,
    "last_updated": "2026-03-08T11:15:52.922385Z"
  },
  {
    "player_name": "Peyton Glavine",
    "team": "Atlanta Braves",
    "level": "Pro",
    "is_client": true,
    "tags": {
      "position": "Pitcher",
      "draft_class": "N/A",
      "roster_priority": 4
    },
    "window": "7d",
    "window_grade": "— Insufficient",
    "stats": {
      "ip": "--",
      "k": "--",
      "bb": "--",
      "era": "--",
      "whip": "--",
      "k_per_9": "--",
      "bb_per_9": "--",
      "k_pct": "--",
      "bb_pct": "--"
    },
    "games_played": 0,
    "last_updated": "2026-03-08T11:15:52.927442Z"
  },
  {
    "player_name": "Tanner Gordon",
    "team": "Colorado Rockies",
    "level": "Pro",
    "is_client": true,
    "tags": {
      "position": "Pitcher",
      "draft_class": "N/A",
      "roster_priority": 2
    },
    "window": "7d",
    "window_grade": "— Insufficient",
    "stats": {
      "ip": "--",
      "k": "--",
      "bb": "--",
      "era": "--",
      "whip": "--",
      "k_per_9": "--",
      "bb_per_9": "--",
      "k_pct": "--",
      "bb_pct": "--"
    },
    "games_played": 0,
    "last_updated": "2026-03-08T11:15:53.302311Z"
  },
  {
    "player_name": "Xavier Kolhosser",
    "team": "Minnesota Twins",
    "level": "Pro",
    "is_client": true,
    "tags": {
      "position": "Pitcher",
      "draft_class": "N/A",
      "roster_priority": 3
    },
    "window": "7d",
    "window_grade": "— Insufficient",
    "stats": {
      "ip": "--",
      "k": "--",
      "bb": "--",
      "era": "--",
      "whip": "--",
      "k_per_9": "--",
      "bb_per_9": "--",
      "k_pct": "--",
      "bb_pct": "--"
    },
    "games_played": 0,
    "last_updated": "2026-03-08T11:15:53.308892Z"
  },
  {
    "player_name": "Aiden Robbins",
    "team": "Texas",
    "level": "NCAA",
    "is_client": true,
    "tags": {
      "position": "Hitter",
      "draft_class": "2026",
      "roster_priority": 1
    },
    "window": "7d",
    "window_grade": "🔥 Hot",
    "stats": {
      "pa": 19,
      "ab": 16,
      "h": 6,
      "hr": 2,
      "rbi": 8,
      "r": 7,
      "sb": 0,
      "avg": ".375",
      "obp": ".474",
      "slg": ".750",
      "ops": "1.224",
      "k_pct": "21.1%",
      "bb_pct": "15.8%"
    },
    "games_played": 4,
    "last_updated": "2026-03-10T04:41:24.196959Z",
    "game_log": [
      {
        "date": "2026-03-08",
        "opponent": "vs USC Upstate",
        "stats": {
          "h": 0,
          "ab": 4,
          "hr": 0,
          "rbi": 0,
          "r": 0,
          "bb": 0,
          "k": 2,
          "sb": 0
        }
      },
      {
        "date": "2026-03-07",
        "opponent": "vs USC Upstate",
        "stats": {
          "h": 1,
          "ab": 5,
          "hr": 1,
          "rbi": 3,
          "r": 2,
          "bb": 0,
          "k": 2,
          "sb": 0
        }
      },
      {
        "date": "2026-03-06",
        "opponent": "vs USC Upstate",
        "stats": {
          "h": 3,
          "ab": 3,
          "hr": 1,
          "rbi": 3,
          "r": 4,
          "bb": 2,
          "k": 0,
          "sb": 0
        }
      },
      {
        "date": "2026-03-03",
        "opponent": "vs Houston Christian",
        "stats": {
          "h": 2,
          "ab": 4,
          "hr": 0,
          "rbi": 2,
          "r": 1,
          "bb": 1,
          "k": 0,
          "sb": 0
        }
      }
    ]
  },
  {
    "player_name": "Cam Flukey",
    "team": "Coastal Carolina",
    "level": "NCAA",
    "is_client": true,
    "tags": {
      "position": "Pitcher",
      "draft_class": "2026",
      "roster_priority": 1
    },
    "window": "7d",
    "window_grade": "— Insufficient",
    "stats": {
      "ip": "--",
      "k": "--",
      "bb": "--",
      "era": "--",
      "whip": "--",
      "k_per_9": "--",
      "bb_per_9": "--",
      "k_pct": "--",
      "bb_pct": "--"
    },
    "games_played": 0,
    "last_updated": "2026-03-10T04:41:24.196978Z"
  },
  {
    "player_name": "Kyle Jones",
    "team": "Florida",
    "level": "NCAA",
    "is_client": true,
    "tags": {
      "position": "Hitter",
      "draft_class": "2026",
      "roster_priority": 1
    },
    "window": "7d",
    "window_grade": "✅ Solid",
    "stats": {
      "pa": 19,
      "ab": 19,
      "h": 6,
      "hr": 1,
      "rbi": 3,
      "r": 3,
      "sb": 0,
      "avg": ".316",
      "obp": ".316",
      "slg": ".474",
      "ops": ".789",
      "k_pct": "21.1%",
      "bb_pct": "0.0%"
    },
    "games_played": 5,
    "last_updated": "2026-03-10T04:41:24.197109Z",
    "game_log": [
      {
        "date": "2026-03-08",
        "opponent": "vs High Point",
        "stats": {
          "h": 2,
          "ab": 5,
          "hr": 1,
          "rbi": 1,
          "r": 2,
          "bb": 0,
          "k": 1,
          "sb": 0
        }
      },
      {
        "date": "2026-03-07",
        "opponent": "vs High Point",
        "stats": {
          "h": 1,
          "ab": 4,
          "hr": 0,
          "rbi": 1,
          "r": 0,
          "bb": 0,
          "k": 0,
          "sb": 0
        }
      },
      {
        "date": "2026-03-06",
        "opponent": "vs High Point",
        "stats": {
          "h": 1,
          "ab": 4,
          "hr": 0,
          "rbi": 1,
          "r": 0,
          "bb": 0,
          "k": 0,
          "sb": 0
        }
      },
      {
        "date": "2026-03-04",
        "opponent": "vs Florida",
        "stats": {
          "h": 0,
          "ab": 1,
          "hr": 0,
          "rbi": 0,
          "r": 0,
          "bb": 0,
          "k": 1,
          "sb": 0
        }
      },
      {
        "date": "2026-03-03",
        "opponent": "vs Florida",
        "stats": {
          "h": 2,
          "ab": 5,
          "hr": 0,
          "rbi": 0,
          "r": 1,
          "bb": 0,
          "k": 2,
          "sb": 0
        }
      }
    ]
  },
  {
    "player_name": "Myles Bailey",
    "team": "Florida State",
    "level": "NCAA",
    "is_client": true,
    "tags": {
      "position": "Hitter",
      "draft_class": "2026",
      "roster_priority": 1
    },
    "window": "7d",
    "window_grade": "🔥 Hot",
    "stats": {
      "pa": 22,
      "ab": 15,
      "h": 6,
      "hr": 2,
      "rbi": 8,
      "r": 7,
      "sb": 0,
      "avg": ".400",
      "obp": ".591",
      "slg": ".800",
      "ops": "1.391",
      "k_pct": "31.8%",
      "bb_pct": "31.8%"
    },
    "games_played": 5,
    "last_updated": "2026-03-10T04:41:24.197227Z",
    "game_log": [
      {
        "date": "2026-03-08",
        "opponent": "vs Northern Kentucky",
        "stats": {
          "h": 2,
          "ab": 3,
          "hr": 1,
          "rbi": 3,
          "r": 3,
          "bb": 2,
          "k": 1,
          "sb": 0
        }
      },
      {
        "date": "2026-03-07",
        "opponent": "vs Northern Kentucky",
        "stats": {
          "h": 2,
          "ab": 2,
          "hr": 1,
          "rbi": 3,
          "r": 2,
          "bb": 3,
          "k": 0,
          "sb": 0
        }
      },
      {
        "date": "2026-03-06",
        "opponent": "vs Northern Kentucky",
        "stats": {
          "h": 0,
          "ab": 4,
          "hr": 0,
          "rbi": 1,
          "r": 0,
          "bb": 1,
          "k": 2,
          "sb": 0
        }
      },
      {
        "date": "2026-03-04",
        "opponent": "vs Mercer",
        "stats": {
          "h": 1,
          "ab": 2,
          "hr": 0,
          "rbi": 0,
          "r": 1,
          "bb": 1,
          "k": 1,
          "sb": 0
        }
      },
      {
        "date": "2026-03-03",
        "opponent": "vs Jacksonville",
        "stats": {
          "h": 1,
          "ab": 4,
          "hr": 0,
          "rbi": 1,
          "r": 1,
          "bb": 0,
          "k": 3,
          "sb": 0
        }
      }
    ]
  },
  {
    "player_name": "Caleb Daniel",
    "team": "Georgia Tech",
    "level": "NCAA",
    "is_client": true,
    "tags": {
      "position": "Hitter",
      "draft_class": "2027",
      "roster_priority": 2
    },
    "window": "7d",
    "window_grade": "🔥 Hot",
    "stats": {
      "pa": 15,
      "ab": 12,
      "h": 6,
      "hr": 2,
      "rbi": 4,
      "r": 3,
      "sb": 0,
      "avg": ".500",
      "obp": ".600",
      "slg": "1.000",
      "ops": "1.600",
      "k_pct": "26.7%",
      "bb_pct": "20.0%"
    },
    "games_played": 4,
    "last_updated": "2026-03-10T04:41:24.197351Z",
    "game_log": [
      {
        "date": "2026-03-08",
        "opponent": "vs Virginia Tech",
        "stats": {
          "h": 1,
          "ab": 1,
          "hr": 0,
          "rbi": 0,
          "r": 0,
          "bb": 1,
          "k": 0,
          "sb": 0
        }
      },
      {
        "date": "2026-03-07",
        "opponent": "vs Virginia Tech",
        "stats": {
          "h": 2,
          "ab": 5,
          "hr": 2,
          "rbi": 2,
          "r": 2,
          "bb": 0,
          "k": 3,
          "sb": 0
        }
      },
      {
        "date": "2026-03-06",
        "opponent": "vs Virginia Tech",
        "stats": {
          "h": 1,
          "ab": 2,
          "hr": 0,
          "rbi": 2,
          "r": 1,
          "bb": 1,
          "k": 1,
          "sb": 0
        }
      },
      {
        "date": "2026-03-03",
        "opponent": "vs Georgia State",
        "stats": {
          "h": 2,
          "ab": 4,
          "hr": 0,
          "rbi": 0,
          "r": 0,
          "bb": 1,
          "k": 0,
          "sb": 0
        }
      }
    ]
  },
  {
    "player_name": "Joe Tiroly",
    "team": "Virginia",
    "level": "NCAA",
    "is_client": true,
    "tags": {
      "position": "Hitter",
      "draft_class": "2026",
      "roster_priority": 2
    },
    "window": "7d",
    "window_grade": "😐 Steady",
    "stats": {
      "pa": 23,
      "ab": 23,
      "h": 8,
      "hr": 0,
      "rbi": 4,
      "r": 4,
      "sb": 0,
      "avg": ".348",
      "obp": ".348",
      "slg": ".348",
      "ops": ".696",
      "k_pct": "26.1%",
      "bb_pct": "0.0%"
    },
    "games_played": 5,
    "last_updated": "2026-03-10T04:41:24.197472Z",
    "game_log": [
      {
        "date": "2026-03-08",
        "opponent": "vs North Carolina",
        "stats": {
          "h": 2,
          "ab": 6,
          "hr": 0,
          "rbi": 0,
          "r": 0,
          "bb": 0,
          "k": 0,
          "sb": 0
        }
      },
      {
        "date": "2026-03-07",
        "opponent": "vs North Carolina",
        "stats": {
          "h": 3,
          "ab": 4,
          "hr": 0,
          "rbi": 2,
          "r": 2,
          "bb": 0,
          "k": 0,
          "sb": 0
        }
      },
      {
        "date": "2026-03-06",
        "opponent": "vs North Carolina",
        "stats": {
          "h": 1,
          "ab": 5,
          "hr": 0,
          "rbi": 0,
          "r": 1,
          "bb": 0,
          "k": 2,
          "sb": 0
        }
      },
      {
        "date": "2026-03-04",
        "opponent": "vs Charlotte",
        "stats": {
          "h": 2,
          "ab": 5,
          "hr": 0,
          "rbi": 2,
          "r": 1,
          "bb": 0,
          "k": 1,
          "sb": 0
        }
      },
      {
        "date": "2026-03-03",
        "opponent": "vs Charlotte",
        "stats": {
          "h": 0,
          "ab": 3,
          "hr": 0,
          "rbi": 0,
          "r": 0,
          "bb": 0,
          "k": 3,
          "sb": 0
        }
      }
    ]
  },
  {
    "player_name": "Riley Goodman",
    "team": "South Carolina",
    "level": "NCAA",
    "is_client": true,
    "tags": {
      "position": "Pitcher",
      "draft_class": "2027",
      "roster_priority": 2
    },
    "window": "7d",
    "window_grade": "😐 Steady",
    "stats": {
      "ip": "4",
      "k": 2,
      "bb": 0,
      "era": "4.50",
      "whip": "1.00",
      "k_per_9": "4.5",
      "bb_per_9": "0.0",
      "k_pct": "12.5%",
      "bb_pct": "0.0%"
    },
    "games_played": 1,
    "last_updated": "2026-03-10T04:41:24.197524Z",
    "game_log": [
      {
        "date": "2026-03-07",
        "opponent": "vs Princeton",
        "stats": {
          "ip": "4.0",
          "er": 2,
          "k": 2,
          "bb": 0,
          "h": 4
        }
      }
    ]
  },
  {
    "player_name": "Will Rhine",
    "team": "Alabama",
    "level": "NCAA",
    "is_client": true,
    "tags": {
      "position": "Hitter",
      "draft_class": "2028",
      "roster_priority": 2
    },
    "window": "7d",
    "window_grade": "— Insufficient",
    "stats": {
      "pa": "--",
      "ab": "--",
      "h": "--",
      "hr": "--",
      "rbi": "--",
      "r": "--",
      "sb": "--",
      "avg": "--",
      "obp": "--",
      "slg": "--",
      "ops": "--",
      "k_pct": "--",
      "bb_pct": "--"
    },
    "games_played": 0,
    "last_updated": "2026-03-10T04:41:24.197534Z"
  },
  {
    "player_name": "Adam McKelvey",
    "team": "Georgia Tech",
    "level": "NCAA",
    "is_client": true,
    "tags": {
      "position": "Pitcher",
      "draft_class": "2027",
      "roster_priority": 3
    },
    "window": "7d",
    "window_grade": "— Insufficient",
    "stats": {
      "ip": "--",
      "k": "--",
      "bb": "--",
      "era": "--",
      "whip": "--",
      "k_per_9": "--",
      "bb_per_9": "--",
      "k_pct": "--",
      "bb_pct": "--"
    },
    "games_played": 0,
    "last_updated": "2026-03-10T04:41:24.197564Z"
  },
  {
    "player_name": "Alex Kranzler",
    "team": "Vanderbilt",
    "level": "NCAA",
    "is_client": true,
    "tags": {
      "position": "Pitcher",
      "draft_class": "2026",
      "roster_priority": 3
    },
    "window": "7d",
    "window_grade": "🥶 Cold",
    "stats": {
      "ip": "4.1",
      "k": 5,
      "bb": 0,
      "era": "8.31",
      "whip": "1.15",
      "k_per_9": "10.4",
      "bb_per_9": "0.0",
      "k_pct": "27.8%",
      "bb_pct": "0.0%"
    },
    "games_played": 1,
    "last_updated": "2026-03-10T04:41:24.197607Z",
    "game_log": [
      {
        "date": "2026-03-03",
        "opponent": "vs Central Arkansas",
        "stats": {
          "ip": "4.1",
          "er": 4,
          "k": 5,
          "bb": 0,
          "h": 5
        }
      }
    ]
  },
  {
    "player_name": "Ben Tryon",
    "team": "Dallas Baptist",
    "level": "NCAA",
    "is_client": true,
    "tags": {
      "position": "Hitter",
      "draft_class": "2026",
      "roster_priority": 3
    },
    "window": "7d",
    "window_grade": "🔥 Hot",
    "stats": {
      "pa": 21,
      "ab": 17,
      "h": 7,
      "hr": 1,
      "rbi": 2,
      "r": 4,
      "sb": 0,
      "avg": ".412",
      "obp": ".524",
      "slg": ".588",
      "ops": "1.112",
      "k_pct": "14.3%",
      "bb_pct": "19.0%"
    },
    "games_played": 5,
    "last_updated": "2026-03-10T04:41:24.197722Z",
    "game_log": [
      {
        "date": "2026-03-08",
        "opponent": "vs Louisiana",
        "stats": {
          "h": 2,
          "ab": 3,
          "hr": 1,
          "rbi": 2,
          "r": 3,
          "bb": 1,
          "k": 0,
          "sb": 0
        }
      },
      {
        "date": "2026-03-07",
        "opponent": "vs Louisiana",
        "stats": {
          "h": 2,
          "ab": 3,
          "hr": 0,
          "rbi": 0,
          "r": 1,
          "bb": 1,
          "k": 0,
          "sb": 0
        }
      },
      {
        "date": "2026-03-06",
        "opponent": "vs Louisiana",
        "stats": {
          "h": 1,
          "ab": 5,
          "hr": 0,
          "rbi": 0,
          "r": 0,
          "bb": 0,
          "k": 3,
          "sb": 0
        }
      },
      {
        "date": "2026-03-04",
        "opponent": "vs Oklahoma",
        "stats": {
          "h": 1,
          "ab": 3,
          "hr": 0,
          "rbi": 0,
          "r": 0,
          "bb": 1,
          "k": 0,
          "sb": 0
        }
      },
      {
        "date": "2026-03-03",
        "opponent": "vs Oklahoma",
        "stats": {
          "h": 1,
          "ab": 3,
          "hr": 0,
          "rbi": 0,
          "r": 0,
          "bb": 1,
          "k": 0,
          "sb": 0
        }
      }
    ]
  },
  {
    "player_name": "Boston Torres",
    "team": "Wake Forest",
    "level": "NCAA",
    "is_client": true,
    "tags": {
      "position": "Hitter",
      "draft_class": "2026",
      "roster_priority": 3
    },
    "window": "7d",
    "window_grade": "— Insufficient",
    "stats": {
      "pa": "--",
      "ab": "--",
      "h": "--",
      "hr": "--",
      "rbi": "--",
      "r": "--",
      "sb": "--",
      "avg": "--",
      "obp": "--",
      "slg": "--",
      "ops": "--",
      "k_pct": "--",
      "bb_pct": "--"
    },
    "games_played": 0,
    "last_updated": "2026-03-10T04:41:24.197751Z"
  },
  {
    "player_name": "Brady Neal",
    "team": "Alabama",
    "level": "NCAA",
    "is_client": true,
    "tags": {
      "position": "Hitter",
      "draft_class": "2026",
      "roster_priority": 3
    },
    "window": "7d",
    "window_grade": "🔥 Hot",
    "stats": {
      "pa": 21,
      "ab": 16,
      "h": 8,
      "hr": 2,
      "rbi": 9,
      "r": 7,
      "sb": 0,
      "avg": ".500",
      "obp": ".619",
      "slg": ".875",
      "ops": "1.494",
      "k_pct": "14.3%",
      "bb_pct": "23.8%"
    },
    "games_played": 5,
    "last_updated": "2026-03-10T04:41:24.197854Z",
    "game_log": [
      {
        "date": "2026-03-08",
        "opponent": "vs North Florida",
        "stats": {
          "h": 2,
          "ab": 2,
          "hr": 1,
          "rbi": 5,
          "r": 2,
          "bb": 1,
          "k": 0,
          "sb": 0
        }
      },
      {
        "date": "2026-03-07",
        "opponent": "vs North Florida",
        "stats": {
          "h": 0,
          "ab": 3,
          "hr": 0,
          "rbi": 0,
          "r": 1,
          "bb": 2,
          "k": 1,
          "sb": 0
        }
      },
      {
        "date": "2026-03-06",
        "opponent": "vs North Florida",
        "stats": {
          "h": 3,
          "ab": 4,
          "hr": 0,
          "rbi": 0,
          "r": 1,
          "bb": 1,
          "k": 1,
          "sb": 0
        }
      },
      {
        "date": "2026-03-04",
        "opponent": "vs Alabama State",
        "stats": {
          "h": 2,
          "ab": 4,
          "hr": 0,
          "rbi": 2,
          "r": 1,
          "bb": 0,
          "k": 0,
          "sb": 0
        }
      },
      {
        "date": "2026-03-03",
        "opponent": "vs Jacksonville State",
        "stats": {
          "h": 1,
          "ab": 3,
          "hr": 1,
          "rbi": 2,
          "r": 2,
          "bb": 1,
          "k": 1,
          "sb": 0
        }
      }
    ]
  },
  {
    "player_name": "Brady St. Pierre",
    "team": "SE Louisiana",
    "level": "NCAA",
    "is_client": true,
    "tags": {
      "position": "Pitcher",
      "draft_class": "2027",
      "roster_priority": 3
    },
    "window": "7d",
    "window_grade": "🥶 Cold",
    "stats": {
      "ip": "4",
      "k": 6,
      "bb": 0,
      "era": "6.75",
      "whip": "1.25",
      "k_per_9": "13.5",
      "bb_per_9": "0.0",
      "k_pct": "35.3%",
      "bb_pct": "0.0%"
    },
    "games_played": 1,
    "last_updated": "2026-03-10T04:41:24.197887Z",
    "game_log": [
      {
        "date": "2026-03-06",
        "opponent": "vs Grambling",
        "stats": {
          "ip": "4.0",
          "er": 3,
          "k": 6,
          "bb": 0,
          "h": 5
        }
      }
    ]
  },
  {
    "player_name": "Braydon Kersey",
    "team": "Mercer",
    "level": "NCAA",
    "is_client": true,
    "tags": {
      "position": "Two-Way",
      "draft_class": "2027",
      "roster_priority": 3
    },
    "window": "7d",
    "window_grade": "🔥 Hot",
    "stats": {
      "pa": 9,
      "ab": 9,
      "h": 4,
      "hr": 2,
      "rbi": 7,
      "r": 3,
      "sb": 0,
      "avg": ".444",
      "obp": ".444",
      "slg": "1.111",
      "ops": "1.556",
      "k_pct": "33.3%",
      "bb_pct": "0.0%"
    },
    "games_played": 4,
    "last_updated": "2026-03-10T04:41:24.197996Z",
    "game_log": [
      {
        "date": "2026-03-08",
        "opponent": "vs Alcorn State",
        "stats": {
          "h": 2,
          "ab": 3,
          "hr": 1,
          "rbi": 5,
          "r": 2,
          "bb": 0,
          "k": 1,
          "sb": 0
        }
      },
      {
        "date": "2026-03-07",
        "opponent": "vs Alcorn State",
        "stats": {
          "h": 0,
          "ab": 0,
          "hr": 0,
          "rbi": 0,
          "r": 0,
          "bb": 0,
          "k": 1,
          "sb": 0
        }
      },
      {
        "date": "2026-03-06",
        "opponent": "vs Alcorn State",
        "stats": {
          "h": 1,
          "ab": 3,
          "hr": 1,
          "rbi": 2,
          "r": 1,
          "bb": 0,
          "k": 0,
          "sb": 0
        }
      },
      {
        "date": "2026-03-04",
        "opponent": "vs Florida State",
        "stats": {
          "h": 1,
          "ab": 3,
          "hr": 0,
          "rbi": 0,
          "r": 0,
          "bb": 0,
          "k": 1,
          "sb": 0
        }
      }
    ]
  },
  {
    "player_name": "Brooks Wright",
    "team": "SE Louisiana",
    "level": "NCAA",
    "is_client": true,
    "tags": {
      "position": "Hitter",
      "draft_class": "2026",
      "roster_priority": 3
    },
    "window": "7d",
    "window_grade": "😐 Steady",
    "stats": {
      "pa": 23,
      "ab": 19,
      "h": 5,
      "hr": 0,
      "rbi": 5,
      "r": 6,
      "sb": 0,
      "avg": ".263",
      "obp": ".391",
      "slg": ".263",
      "ops": ".654",
      "k_pct": "26.1%",
      "bb_pct": "17.4%"
    },
    "games_played": 5,
    "last_updated": "2026-03-10T04:41:24.198097Z",
    "game_log": [
      {
        "date": "2026-03-08",
        "opponent": "vs Grambling",
        "stats": {
          "h": 1,
          "ab": 4,
          "hr": 0,
          "rbi": 1,
          "r": 1,
          "bb": 0,
          "k": 1,
          "sb": 0
        }
      },
      {
        "date": "2026-03-07",
        "opponent": "vs Grambling",
        "stats": {
          "h": 1,
          "ab": 4,
          "hr": 0,
          "rbi": 0,
          "r": 0,
          "bb": 0,
          "k": 1,
          "sb": 0
        }
      },
      {
        "date": "2026-03-06",
        "opponent": "vs Grambling",
        "stats": {
          "h": 1,
          "ab": 3,
          "hr": 0,
          "rbi": 1,
          "r": 1,
          "bb": 1,
          "k": 2,
          "sb": 0
        }
      },
      {
        "date": "2026-03-04",
        "opponent": "vs Southeastern Louisiana",
        "stats": {
          "h": 0,
          "ab": 4,
          "hr": 0,
          "rbi": 1,
          "r": 2,
          "bb": 2,
          "k": 1,
          "sb": 0
        }
      },
      {
        "date": "2026-03-03",
        "opponent": "vs Southeastern Louisiana",
        "stats": {
          "h": 2,
          "ab": 4,
          "hr": 0,
          "rbi": 2,
          "r": 2,
          "bb": 1,
          "k": 1,
          "sb": 0
        }
      }
    ]
  },
  {
    "player_name": "Cole Cleveland",
    "team": "FIU",
    "level": "NCAA",
    "is_client": true,
    "tags": {
      "position": "Hitter",
      "draft_class": "2026",
      "roster_priority": 3
    },
    "window": "7d",
    "window_grade": "😐 Steady",
    "stats": {
      "pa": 9,
      "ab": 9,
      "h": 1,
      "hr": 1,
      "rbi": 1,
      "r": 1,
      "sb": 0,
      "avg": ".111",
      "obp": ".111",
      "slg": ".444",
      "ops": ".556",
      "k_pct": "11.1%",
      "bb_pct": "0.0%"
    },
    "games_played": 3,
    "last_updated": "2026-03-10T04:41:24.198164Z",
    "game_log": [
      {
        "date": "2026-03-08",
        "opponent": "vs Florida International",
        "stats": {
          "h": 1,
          "ab": 4,
          "hr": 1,
          "rbi": 1,
          "r": 1,
          "bb": 0,
          "k": 0,
          "sb": 0
        }
      },
      {
        "date": "2026-03-07",
        "opponent": "vs Florida Atlantic",
        "stats": {
          "h": 0,
          "ab": 3,
          "hr": 0,
          "rbi": 0,
          "r": 0,
          "bb": 0,
          "k": 1,
          "sb": 0
        }
      },
      {
        "date": "2026-03-06",
        "opponent": "vs Florida International",
        "stats": {
          "h": 0,
          "ab": 2,
          "hr": 0,
          "rbi": 0,
          "r": 0,
          "bb": 0,
          "k": 0,
          "sb": 0
        }
      }
    ]
  },
  {
    "player_name": "Drew Bellis",
    "team": "UCF",
    "level": "NCAA",
    "is_client": true,
    "tags": {
      "position": "Pitcher",
      "draft_class": "2027",
      "roster_priority": 3
    },
    "window": "7d",
    "window_grade": "— Insufficient",
    "stats": {
      "ip": "--",
      "k": "--",
      "bb": "--",
      "era": "--",
      "whip": "--",
      "k_per_9": "--",
      "bb_per_9": "--",
      "k_pct": "--",
      "bb_pct": "--"
    },
    "games_played": 0,
    "last_updated": "2026-03-10T04:41:24.198171Z"
  },
  {
    "player_name": "Evan Taylor",
    "team": "Alabama",
    "level": "NCAA",
    "is_client": true,
    "tags": {
      "position": "Two-Way",
      "draft_class": "2028",
      "roster_priority": 3
    },
    "window": "7d",
    "window_grade": "— Insufficient",
    "stats": {
      "pa": "--",
      "ab": "--",
      "h": "--",
      "hr": "--",
      "rbi": "--",
      "r": "--",
      "sb": "--",
      "avg": "--",
      "obp": "--",
      "slg": "--",
      "ops": "--",
      "k_pct": "--",
      "bb_pct": "--"
    },
    "games_played": 1,
    "last_updated": "2026-03-10T04:41:24.198206Z",
    "game_log": [
      {
        "date": "2026-03-04",
        "opponent": "vs Alabama State",
        "stats": {
          "h": 0,
          "ab": 1,
          "hr": 0,
          "rbi": 0,
          "r": 0,
          "bb": 0,
          "k": 0,
          "sb": 0
        }
      }
    ]
  },
  {
    "player_name": "Henry Zatkowski",
    "team": "Virginia",
    "level": "NCAA",
    "is_client": true,
    "tags": {
      "position": "Pitcher",
      "draft_class": "2027",
      "roster_priority": 3
    },
    "window": "7d",
    "window_grade": "🥶 Cold",
    "stats": {
      "ip": "5.1",
      "k": 3,
      "bb": 0,
      "era": "5.06",
      "whip": "0.94",
      "k_per_9": "5.1",
      "bb_per_9": "0.0",
      "k_pct": "14.3%",
      "bb_pct": "0.0%"
    },
    "games_played": 1,
    "last_updated": "2026-03-10T04:41:24.198243Z",
    "game_log": [
      {
        "date": "2026-03-06",
        "opponent": "vs North Carolina",
        "stats": {
          "ip": "5.1",
          "er": 3,
          "k": 3,
          "bb": 0,
          "h": 5
        }
      }
    ]
  },
  {
    "player_name": "Lee Ellis",
    "team": "Ohio State",
    "level": "NCAA",
    "is_client": true,
    "tags": {
      "position": "Hitter",
      "draft_class": "2026",
      "roster_priority": 3
    },
    "window": "7d",
    "window_grade": "🥶 Cold",
    "stats": {
      "pa": 14,
      "ab": 13,
      "h": 0,
      "hr": 0,
      "rbi": 2,
      "r": 1,
      "sb": 0,
      "avg": ".000",
      "obp": ".071",
      "slg": ".000",
      "ops": ".071",
      "k_pct": "28.6%",
      "bb_pct": "7.1%"
    },
    "games_played": 4,
    "last_updated": "2026-03-10T04:41:24.198345Z",
    "game_log": [
      {
        "date": "2026-03-08",
        "opponent": "vs UCLA",
        "stats": {
          "h": 0,
          "ab": 3,
          "hr": 0,
          "rbi": 1,
          "r": 0,
          "bb": 0,
          "k": 0,
          "sb": 0
        }
      },
      {
        "date": "2026-03-07",
        "opponent": "vs UCLA",
        "stats": {
          "h": 0,
          "ab": 3,
          "hr": 0,
          "rbi": 0,
          "r": 1,
          "bb": 1,
          "k": 2,
          "sb": 0
        }
      },
      {
        "date": "2026-03-06",
        "opponent": "vs UCLA",
        "stats": {
          "h": 0,
          "ab": 3,
          "hr": 0,
          "rbi": 0,
          "r": 0,
          "bb": 0,
          "k": 1,
          "sb": 0
        }
      },
      {
        "date": "2026-03-04",
        "opponent": "vs Xavier",
        "stats": {
          "h": 0,
          "ab": 4,
          "hr": 0,
          "rbi": 1,
          "r": 0,
          "bb": 0,
          "k": 1,
          "sb": 0
        }
      }
    ]
  },
  {
    "player_name": "Lucas Steele",
    "team": "Auburn",
    "level": "NCAA",
    "is_client": true,
    "tags": {
      "position": "Hitter",
      "draft_class": "2026",
      "roster_priority": 3
    },
    "window": "7d",
    "window_grade": "🥶 Cold",
    "stats": {
      "pa": 8,
      "ab": 8,
      "h": 0,
      "hr": 0,
      "rbi": 0,
      "r": 0,
      "sb": 0,
      "avg": ".000",
      "obp": ".000",
      "slg": ".000",
      "ops": ".000",
      "k_pct": "25.0%",
      "bb_pct": "0.0%"
    },
    "games_played": 2,
    "last_updated": "2026-03-10T04:41:24.198429Z",
    "game_log": [
      {
        "date": "2026-03-07",
        "opponent": "vs Winthrop",
        "stats": {
          "h": 0,
          "ab": 4,
          "hr": 0,
          "rbi": 0,
          "r": 0,
          "bb": 0,
          "k": 1,
          "sb": 0
        }
      },
      {
        "date": "2026-03-06",
        "opponent": "vs Winthrop",
        "stats": {
          "h": 0,
          "ab": 4,
          "hr": 0,
          "rbi": 0,
          "r": 0,
          "bb": 0,
          "k": 1,
          "sb": 0
        }
      }
    ]
  },
  {
    "player_name": "Mason Eckelman",
    "team": "Ohio State",
    "level": "NCAA",
    "is_client": true,
    "tags": {
      "position": "Hitter",
      "draft_class": "2026",
      "roster_priority": 3
    },
    "window": "7d",
    "window_grade": "😐 Steady",
    "stats": {
      "pa": 18,
      "ab": 15,
      "h": 3,
      "hr": 1,
      "rbi": 4,
      "r": 4,
      "sb": 0,
      "avg": ".200",
      "obp": ".333",
      "slg": ".400",
      "ops": ".733",
      "k_pct": "22.2%",
      "bb_pct": "16.7%"
    },
    "games_played": 4,
    "last_updated": "2026-03-10T04:41:24.198515Z",
    "game_log": [
      {
        "date": "2026-03-08",
        "opponent": "vs UCLA",
        "stats": {
          "h": 0,
          "ab": 3,
          "hr": 0,
          "rbi": 0,
          "r": 2,
          "bb": 2,
          "k": 0,
          "sb": 0
        }
      },
      {
        "date": "2026-03-07",
        "opponent": "vs UCLA",
        "stats": {
          "h": 2,
          "ab": 4,
          "hr": 1,
          "rbi": 4,
          "r": 1,
          "bb": 0,
          "k": 2,
          "sb": 0
        }
      },
      {
        "date": "2026-03-06",
        "opponent": "vs UCLA",
        "stats": {
          "h": 1,
          "ab": 4,
          "hr": 0,
          "rbi": 0,
          "r": 0,
          "bb": 0,
          "k": 2,
          "sb": 0
        }
      },
      {
        "date": "2026-03-04",
        "opponent": "vs Xavier",
        "stats": {
          "h": 0,
          "ab": 4,
          "hr": 0,
          "rbi": 0,
          "r": 1,
          "bb": 1,
          "k": 0,
          "sb": 0
        }
      }
    ]
  },
  {
    "player_name": "Michael Gillen",
    "team": "UCF",
    "level": "NCAA",
    "is_client": true,
    "tags": {
      "position": "Pitcher",
      "draft_class": "2026",
      "roster_priority": 3
    },
    "window": "7d",
    "window_grade": "🔥 Hot",
    "stats": {
      "ip": "1",
      "k": 0,
      "bb": 0,
      "era": "0.00",
      "whip": "1.00",
      "k_per_9": "0.0",
      "bb_per_9": "0.0",
      "k_pct": "0.0%",
      "bb_pct": "0.0%"
    },
    "games_played": 2,
    "last_updated": "2026-03-10T04:41:24.198556Z",
    "game_log": [
      {
        "date": "2026-03-08",
        "opponent": "vs Murray State",
        "stats": {
          "ip": "0.2",
          "er": 0,
          "k": 0,
          "bb": 0,
          "h": 1
        }
      },
      {
        "date": "2026-03-04",
        "opponent": "vs Florida Gulf Coast",
        "stats": {
          "ip": "0.1",
          "er": 0,
          "k": 0,
          "bb": 0,
          "h": 0
        }
      }
    ]
  },
  {
    "player_name": "Sam Mitchell",
    "team": "Southern Miss",
    "level": "NCAA",
    "is_client": true,
    "tags": {
      "position": "Pitcher",
      "draft_class": "2028",
      "roster_priority": 3
    },
    "window": "7d",
    "window_grade": "— Insufficient",
    "stats": {
      "ip": "--",
      "k": "--",
      "bb": "--",
      "era": "--",
      "whip": "--",
      "k_per_9": "--",
      "bb_per_9": "--",
      "k_pct": "--",
      "bb_pct": "--"
    },
    "games_played": 1,
    "last_updated": "2026-03-10T04:41:24.198590Z",
    "game_log": [
      {
        "date": "2026-03-03",
        "opponent": "vs Mississippi State",
        "stats": {
          "ip": "0",
          "er": 0,
          "k": 0,
          "bb": 0,
          "h": 1
        }
      }
    ]
  },
  {
    "player_name": "Taylor Kirk",
    "team": "Fordham",
    "level": "NCAA",
    "is_client": true,
    "tags": {
      "position": "Hitter",
      "draft_class": "2027",
      "roster_priority": 3
    },
    "window": "7d",
    "window_grade": "😐 Steady",
    "stats": {
      "pa": 9,
      "ab": 9,
      "h": 3,
      "hr": 0,
      "rbi": 2,
      "r": 3,
      "sb": 3,
      "avg": ".333",
      "obp": ".333",
      "slg": ".333",
      "ops": ".667",
      "k_pct": "0.0%",
      "bb_pct": "0.0%"
    },
    "games_played": 2,
    "last_updated": "2026-03-10T04:41:24.198666Z",
    "game_log": [
      {
        "date": "2026-03-08",
        "opponent": "vs Cornell",
        "stats": {
          "h": 1,
          "ab": 5,
          "hr": 0,
          "rbi": 2,
          "r": 1,
          "bb": 0,
          "k": 0,
          "sb": 1
        }
      },
      {
        "date": "2026-03-07",
        "opponent": "vs Cornell",
        "stats": {
          "h": 2,
          "ab": 4,
          "hr": 0,
          "rbi": 0,
          "r": 2,
          "bb": 0,
          "k": 0,
          "sb": 2
        }
      }
    ]
  },
  {
    "player_name": "Ty Finkbeiner",
    "team": "Michigan",
    "level": "NCAA",
    "is_client": true,
    "tags": {
      "position": "Pitcher",
      "draft_class": "2028",
      "roster_priority": 3
    },
    "window": "7d",
    "window_grade": "— Insufficient",
    "stats": {
      "ip": "--",
      "k": "--",
      "bb": "--",
      "era": "--",
      "whip": "--",
      "k_per_9": "--",
      "bb_per_9": "--",
      "k_pct": "--",
      "bb_pct": "--"
    },
    "games_played": 1,
    "last_updated": "2026-03-10T04:41:24.198705Z",
    "game_log": [
      {
        "date": "2026-03-06",
        "opponent": "vs Pepperdine",
        "stats": {
          "ip": "0.0",
          "er": 1,
          "k": 0,
          "bb": 0,
          "h": 1
        }
      }
    ]
  },
  {
    "player_name": "Brisen Tweedy",
    "team": "USF",
    "level": "NCAA",
    "is_client": true,
    "tags": {
      "position": "Pitcher",
      "draft_class": "2028",
      "roster_priority": 4
    },
    "window": "7d",
    "window_grade": "🥶 Cold",
    "stats": {
      "ip": "2",
      "k": 0,
      "bb": 0,
      "era": "13.50",
      "whip": "1.50",
      "k_per_9": "0.0",
      "bb_per_9": "0.0",
      "k_pct": "0.0%",
      "bb_pct": "0.0%"
    },
    "games_played": 1,
    "last_updated": "2026-03-10T04:41:24.198729Z",
    "game_log": [
      {
        "date": "2026-03-03",
        "opponent": "vs Stetson",
        "stats": {
          "ip": "2",
          "er": 3,
          "k": 0,
          "bb": 0,
          "h": 3
        }
      }
    ]
  },
  {
    "player_name": "Bryce Fowler",
    "team": "Alabama",
    "level": "NCAA",
    "is_client": true,
    "tags": {
      "position": "Hitter",
      "draft_class": "2026",
      "roster_priority": 4
    },
    "window": "7d",
    "window_grade": "🔥 Hot",
    "stats": {
      "pa": 17,
      "ab": 13,
      "h": 6,
      "hr": 1,
      "rbi": 6,
      "r": 3,
      "sb": 0,
      "avg": ".462",
      "obp": ".588",
      "slg": ".692",
      "ops": "1.281",
      "k_pct": "17.6%",
      "bb_pct": "23.5%"
    },
    "games_played": 4,
    "last_updated": "2026-03-10T04:41:24.198825Z",
    "game_log": [
      {
        "date": "2026-03-08",
        "opponent": "vs North Florida",
        "stats": {
          "h": 2,
          "ab": 5,
          "hr": 1,
          "rbi": 2,
          "r": 1,
          "bb": 0,
          "k": 1,
          "sb": 0
        }
      },
      {
        "date": "2026-03-07",
        "opponent": "vs North Florida",
        "stats": {
          "h": 3,
          "ab": 5,
          "hr": 0,
          "rbi": 4,
          "r": 0,
          "bb": 0,
          "k": 0,
          "sb": 0
        }
      },
      {
        "date": "2026-03-04",
        "opponent": "vs Alabama State",
        "stats": {
          "h": 0,
          "ab": 1,
          "hr": 0,
          "rbi": 0,
          "r": 1,
          "bb": 3,
          "k": 1,
          "sb": 0
        }
      },
      {
        "date": "2026-03-03",
        "opponent": "vs Jacksonville State",
        "stats": {
          "h": 1,
          "ab": 2,
          "hr": 0,
          "rbi": 0,
          "r": 1,
          "bb": 1,
          "k": 1,
          "sb": 0
        }
      }
    ]
  },
  {
    "player_name": "Eamon McDermott",
    "team": "Duke",
    "level": "NCAA",
    "is_client": true,
    "tags": {
      "position": "Pitcher",
      "draft_class": "2028",
      "roster_priority": 4
    },
    "window": "7d",
    "window_grade": "— Insufficient",
    "stats": {
      "ip": "--",
      "k": "--",
      "bb": "--",
      "era": "--",
      "whip": "--",
      "k_per_9": "--",
      "bb_per_9": "--",
      "k_pct": "--",
      "bb_pct": "--"
    },
    "games_played": 0,
    "last_updated": "2026-03-10T04:41:24.198833Z"
  },
  {
    "player_name": "Lee Sowers",
    "team": "North Carolina",
    "level": "NCAA",
    "is_client": true,
    "tags": {
      "position": "Hitter",
      "draft_class": "2027",
      "roster_priority": 4
    },
    "window": "7d",
    "window_grade": "— Insufficient",
    "stats": {
      "pa": "--",
      "ab": "--",
      "h": "--",
      "hr": "--",
      "rbi": "--",
      "r": "--",
      "sb": "--",
      "avg": "--",
      "obp": "--",
      "slg": "--",
      "ops": "--",
      "k_pct": "--",
      "bb_pct": "--"
    },
    "games_played": 2,
    "last_updated": "2026-03-10T04:41:24.198887Z",
    "game_log": [
      {
        "date": "2026-03-08",
        "opponent": "vs Virginia",
        "stats": {
          "h": 1,
          "ab": 1,
          "hr": 0,
          "rbi": 0,
          "r": 0,
          "bb": 0,
          "k": 0,
          "sb": 0
        }
      },
      {
        "date": "2026-03-07",
        "opponent": "vs Virginia",
        "stats": {
          "h": 1,
          "ab": 1,
          "hr": 0,
          "rbi": 0,
          "r": 0,
          "bb": 0,
          "k": 0,
          "sb": 0
        }
      }
    ]
  },
  {
    "player_name": "Luke Fithian",
    "team": "Rutgers",
    "level": "NCAA",
    "is_client": true,
    "tags": {
      "position": "Pitcher",
      "draft_class": "2027",
      "roster_priority": 4
    },
    "window": "7d",
    "window_grade": "— Insufficient",
    "stats": {
      "ip": "--",
      "k": "--",
      "bb": "--",
      "era": "--",
      "whip": "--",
      "k_per_9": "--",
      "bb_per_9": "--",
      "k_pct": "--",
      "bb_pct": "--"
    },
    "games_played": 0,
    "last_updated": "2026-03-10T04:41:24.198894Z"
  },
  {
    "player_name": "Sam Harry",
    "team": "Sacramento State",
    "level": "NCAA",
    "is_client": true,
    "tags": {
      "position": "Hitter",
      "draft_class": "2028",
      "roster_priority": 4
    },
    "window": "7d",
    "window_grade": "🥶 Cold",
    "stats": {
      "pa": 17,
      "ab": 15,
      "h": 3,
      "hr": 0,
      "rbi": 1,
      "r": 2,
      "sb": 0,
      "avg": ".200",
      "obp": ".294",
      "slg": ".200",
      "ops": ".494",
      "k_pct": "29.4%",
      "bb_pct": "11.8%"
    },
    "games_played": 4,
    "last_updated": "2026-03-10T04:41:24.198992Z",
    "game_log": [
      {
        "date": "2026-03-08",
        "opponent": "vs LSU",
        "stats": {
          "h": 1,
          "ab": 4,
          "hr": 0,
          "rbi": 1,
          "r": 1,
          "bb": 1,
          "k": 1,
          "sb": 0
        }
      },
      {
        "date": "2026-03-07",
        "opponent": "vs LSU",
        "stats": {
          "h": 1,
          "ab": 5,
          "hr": 0,
          "rbi": 0,
          "r": 0,
          "bb": 0,
          "k": 2,
          "sb": 0
        }
      },
      {
        "date": "2026-03-06",
        "opponent": "vs LSU",
        "stats": {
          "h": 0,
          "ab": 2,
          "hr": 0,
          "rbi": 0,
          "r": 1,
          "bb": 1,
          "k": 1,
          "sb": 0
        }
      },
      {
        "date": "2026-03-03",
        "opponent": "vs Fresno State",
        "stats": {
          "h": 1,
          "ab": 4,
          "hr": 0,
          "rbi": 0,
          "r": 0,
          "bb": 0,
          "k": 1,
          "sb": 0
        }
      }
    ]
  },
  {
    "player_name": "Truitt Webb",
    "team": "SE Louisiana",
    "level": "NCAA",
    "is_client": true,
    "tags": {
      "position": "Pitcher",
      "draft_class": "2027",
      "roster_priority": 4
    },
    "window": "7d",
    "window_grade": "🔥 Hot",
    "stats": {
      "ip": "1",
      "k": 3,
      "bb": 0,
      "era": "0.00",
      "whip": "0.00",
      "k_per_9": "27.0",
      "bb_per_9": "0.0",
      "k_pct": "100.0%",
      "bb_pct": "0.0%"
    },
    "games_played": 1,
    "last_updated": "2026-03-10T04:41:24.199034Z",
    "game_log": [
      {
        "date": "2026-03-07",
        "opponent": "vs Grambling",
        "stats": {
          "ip": "1.0",
          "er": 0,
          "k": 3,
          "bb": 0,
          "h": 0
        }
      }
    ]
  },
  {
    "player_name": "Zack Johnson",
    "team": "Alabama",
    "level": "NCAA",
    "is_client": true,
    "tags": {
      "position": "Hitter",
      "draft_class": "2028",
      "roster_priority": 4
    },
    "window": "7d",
    "window_grade": "— Insufficient",
    "stats": {
      "pa": "--",
      "ab": "--",
      "h": "--",
      "hr": "--",
      "rbi": "--",
      "r": "--",
      "sb": "--",
      "avg": "--",
      "obp": "--",
      "slg": "--",
      "ops": "--",
      "k_pct": "--",
      "bb_pct": "--"
    },
    "games_played": 1,
    "last_updated": "2026-03-10T04:41:24.199061Z",
    "game_log": [
      {
        "date": "2026-03-03",
        "opponent": "vs Jacksonville State",
        "stats": {
          "h": 0,
          "ab": 4,
          "hr": 0,
          "rbi": 0,
          "r": 0,
          "bb": 0,
          "k": 2,
          "sb": 0
        }
      }
    ]
  },
  {
    "player_name": "Duke McCarron",
    "team": "Saint Josephs",
    "level": "NCAA",
    "is_client": true,
    "tags": {
      "position": "Pitcher",
      "draft_class": "2026",
      "roster_priority": 3
    },
    "window": "7d",
    "window_grade": "🔥 Hot",
    "stats": {
      "ip": "5",
      "k": 7,
      "bb": 0,
      "era": "0.00",
      "whip": "0.40",
      "k_per_9": "12.6",
      "bb_per_9": "0.0",
      "k_pct": "41.2%",
      "bb_pct": "0.0%"
    },
    "games_played": 1,
    "last_updated": "2026-03-10T04:41:24.199098Z",
    "game_log": [
      {
        "date": "2026-03-06",
        "opponent": "vs Bucknell",
        "stats": {
          "ip": "5.0",
          "er": 0,
          "k": 7,
          "bb": 0,
          "h": 2
        }
      }
    ]
  },
  {
    "player_name": "Tanner Chun",
    "team": "Tulane",
    "level": "NCAA",
    "is_client": true,
    "tags": {
      "position": "Hitter",
      "draft_class": "2027",
      "roster_priority": 3
    },
    "window": "7d",
    "window_grade": "🥶 Cold",
    "stats": {
      "pa": 10,
      "ab": 10,
      "h": 1,
      "hr": 0,
      "rbi": 0,
      "r": 1,
      "sb": 0,
      "avg": ".100",
      "obp": ".100",
      "slg": ".100",
      "ops": ".200",
      "k_pct": "10.0%",
      "bb_pct": "0.0%"
    },
    "games_played": 3,
    "last_updated": "2026-03-10T04:41:24.199169Z",
    "game_log": [
      {
        "date": "2026-03-08",
        "opponent": "vs TCU",
        "stats": {
          "h": 1,
          "ab": 3,
          "hr": 0,
          "rbi": 0,
          "r": 1,
          "bb": 0,
          "k": 0,
          "sb": 0
        }
      },
      {
        "date": "2026-03-06",
        "opponent": "vs TCU",
        "stats": {
          "h": 0,
          "ab": 4,
          "hr": 0,
          "rbi": 0,
          "r": 0,
          "bb": 0,
          "k": 1,
          "sb": 0
        }
      },
      {
        "date": "2026-03-03",
        "opponent": "vs Nicholls",
        "stats": {
          "h": 0,
          "ab": 3,
          "hr": 0,
          "rbi": 0,
          "r": 0,
          "bb": 0,
          "k": 0,
          "sb": 0
        }
      }
    ]
  }
]