{
  "generated_at": "2026-04-03T06:21:24.408525+00:00",
  "source_date": "2026-04-01",
  "players": [
    {
      "player_name": "Garrett Whitlock",
      "team": "Boston Red Sox",
      "level": "Pro",
      "stats_summary": "1.0 IP, 1 H, 0 ER, 1 K, 2 BB",
      "game_context": "Boston Red Sox 4, Houston Astros 6 | Final",
      "game_status": "Final",
      "game_time": "2:10 PM ET",
      "game_date": "2026-04-01",
      "is_yesterday": false,
      "next_game": {
        "date": "Fri 04/03",
        "date_full": "2026-04-03",
        "opponent": "San Diego Padres",
        "home_away": "vs",
        "time": "2:10 PM ET",
        "display": "vs San Diego Padres - Fri 04/03 2:10 PM ET"
      },
      "box_score_url": "https://www.mlb.com/gameday/824211",
      "player_profile_url": "https://www.mlb.com/player/676477",
      "performance_grade": "😐 Routine",
      "grade_reason": "1 IP, 0 ER",
      "social_search_url": "https://x.com/search?q=%22Garrett%20Whitlock%22%20Sox&f=live",
      "data_source": "MLB Stats API",
      "is_client": true,
      "tags": {
        "draft_class": "N/A",
        "position": "Pitcher",
        "roster_priority": 1
      }
    },
    {
      "player_name": "Boston Torres",
      "team": "Wake Forest",
      "level": "NCAA",
      "stats_summary": "2-3, 2 RBI, K",
      "game_context": "Clemson 4, Wake Forest 15 | Final",
      "game_status": "Final",
      "game_time": null,
      "game_date": "2026-04-01",
      "is_yesterday": false,
      "next_game": null,
      "box_score_url": "https://stats.statbroadcast.com/broadcast/?id=636529",
      "player_profile_url": "https://www.google.com/search?q=site%3Athebaseballcube.com%20%22Boston%20Torres%22&btnI=",
      "performance_grade": "✅ Good",
      "grade_reason": "2 hits",
      "social_search_url": "https://x.com/search?q=%22Boston%20Torres%22%20Wake%20Forest&f=live",
      "data_source": "D1Baseball",
      "is_client": true,
      "tags": {
        "draft_class": "2026",
        "position": "Hitter",
        "roster_priority": 3
      }
    },
    {
      "player_name": "Dane Moehler",
      "team": "Clemson",
      "level": "NCAA",
      "stats_summary": "Did Not Play",
      "game_context": "Clemson 4, Wake Forest 15 | Final",
      "game_status": "Final",
      "game_time": null,
      "game_date": "2026-04-01",
      "is_yesterday": false,
      "next_game": null,
      "box_score_url": "https://godeacs.com/boxscore.aspx?id=14571",
      "player_profile_url": "https://www.google.com/search?q=site%3Athebaseballcube.com%20%22Dane%20Moehler%22&btnI=",
      "performance_grade": "— DNP",
      "grade_reason": "",
      "social_search_url": "https://x.com/search?q=%22Dane%20Moehler%22%20Clemson&f=live",
      "data_source": "D1Baseball",
      "is_client": false,
      "tags": {
        "draft_class": "2027",
        "position": "Pitcher",
        "roster_priority": 2
      }
    },
    {
      "player_name": "Chase Petty",
      "team": "Louisville Bats",
      "level": "Pro",
      "stats_summary": "1.2 IP, 5 H, 7 ER, 2 K, 2 BB, 2 HR, L",
      "game_context": "Iowa Cubs 12, Louisville Bats 7 | Final",
      "game_status": "Final",
      "game_time": "12:05 PM ET",
      "game_date": "2026-04-01",
      "is_yesterday": false,
      "next_game": {
        "date": "Thu 04/02",
        "date_full": "2026-04-02",
        "opponent": "Iowa Cubs",
        "home_away": "vs",
        "time": "6:35 PM ET",
        "display": "vs Iowa Cubs - Thu 04/02 6:35 PM ET"
      },
      "box_score_url": "https://www.mlb.com/gameday/816293",
      "player_profile_url": "https://www.mlb.com/player/695534",
      "performance_grade": "🚩 Off Day",
      "grade_reason": "7 earned runs allowed in 1.2 IP",
      "social_search_url": "https://x.com/search?q=%22Chase%20Petty%22%20Reds&f=live",
      "data_source": "MLB Stats API",
      "is_client": false,
      "tags": {
        "draft_class": "",
        "position": "RHP",
        "roster_priority": 1
      }
    },
    {
      "player_name": "Bo Lowrance",
      "team": "Christ Church",
      "level": "HS",
      "stats_summary": "1-2, 1 R, 2 BB",
      "game_context": "W 7-4",
      "game_status": "Final",
      "game_time": null,
      "game_date": "2026-04-01",
      "is_yesterday": true,
      "next_game": null,
      "box_score_url": null,
      "player_profile_url": null,
      "performance_grade": "✅ Good",
      "grade_reason": "Reached base 3 times",
      "social_search_url": "https://x.com/search?q=%22Bo%20Lowrance%22%20Christ%20Church&f=live",
      "data_source": "HS Sheet",
      "is_client": true,
      "tags": {
        "draft_class": "2026",
        "position": "Hitter",
        "roster_priority": 1
      }
    },
    {
      "player_name": "Max Phillips",
      "team": "Trinity",
      "level": "HS",
      "stats_summary": "1-2, 2 R, 1 BB",
      "game_context": "W 10-0",
      "game_status": "Final",
      "game_time": null,
      "game_date": "2026-04-01",
      "is_yesterday": true,
      "next_game": null,
      "box_score_url": null,
      "player_profile_url": null,
      "performance_grade": "✅ Good",
      "grade_reason": "Productive game",
      "social_search_url": "https://x.com/search?q=%22Max%20Phillips%22%20Trinity&f=live",
      "data_source": "HS Sheet",
      "is_client": true,
      "tags": {
        "draft_class": "2027",
        "position": "Hitter",
        "roster_priority": 1
      }
    },
    {
      "player_name": "Taj Marchand",
      "team": "James Island",
      "level": "HS",
      "stats_summary": "1-2, 3 RBI, 2 R, 2 BB",
      "game_context": "W 13-1",
      "game_status": "Final",
      "game_time": null,
      "game_date": "2026-04-01",
      "is_yesterday": true,
      "next_game": null,
      "box_score_url": null,
      "player_profile_url": null,
      "performance_grade": "🔥 Standout",
      "grade_reason": "3 RBI",
      "social_search_url": "https://x.com/search?q=%22Taj%20Marchand%22%20James%20Island&f=live",
      "data_source": "HS Sheet",
      "is_client": true,
      "tags": {
        "draft_class": "2026",
        "position": "Hitter",
        "roster_priority": 1
      }
    },
    {
      "player_name": "Colin Raymond",
      "team": "Stony Brook",
      "level": "HS",
      "stats_summary": "1-2, 1 RBI, 2 R, 2 BB",
      "game_context": "W 11-2",
      "game_status": "Final",
      "game_time": null,
      "game_date": "2026-04-01",
      "is_yesterday": true,
      "next_game": null,
      "box_score_url": null,
      "player_profile_url": null,
      "performance_grade": "🔥 Standout",
      "grade_reason": "Extra-base hit (double)",
      "social_search_url": "https://x.com/search?q=%22Colin%20Raymond%22%20Stony%20Brook&f=live",
      "data_source": "HS Sheet",
      "is_client": true,
      "tags": {
        "draft_class": "2028",
        "position": "Hitter",
        "roster_priority": 2
      }
    },
    {
      "player_name": "Hunter Wieckowski",
      "team": "Timber Creek",
      "level": "HS",
      "stats_summary": "3 IP, 5 K, 5 ER",
      "game_context": "L 7-1",
      "game_status": "Final",
      "game_time": null,
      "game_date": "2026-04-01",
      "is_yesterday": true,
      "next_game": null,
      "box_score_url": null,
      "player_profile_url": null,
      "performance_grade": "🚩 Off Day",
      "grade_reason": "5 earned runs allowed in 3 IP",
      "social_search_url": "https://x.com/search?q=%22Hunter%20Wieckowski%22%20Timber%20Creek&f=live",
      "data_source": "HS Sheet",
      "is_client": true,
      "tags": {
        "draft_class": "2027",
        "position": "Pitcher",
        "roster_priority": 2
      }
    },
    {
      "player_name": "Jace Moran",
      "team": "Suwannee",
      "level": "HS",
      "stats_summary": "4-4, 1 RBI, 1 R",
      "game_context": "W 16-2",
      "game_status": "Final",
      "game_time": null,
      "game_date": "2026-04-01",
      "is_yesterday": true,
      "next_game": null,
      "box_score_url": null,
      "player_profile_url": null,
      "performance_grade": "🔥 Standout",
      "grade_reason": "4 hits",
      "social_search_url": "https://x.com/search?q=%22Jace%20Moran%22%20Suwannee&f=live",
      "data_source": "HS Sheet",
      "is_client": true,
      "tags": {
        "draft_class": "2027",
        "position": "Hitter",
        "roster_priority": 2
      }
    },
    {
      "player_name": "Chris Grasso",
      "team": "St. Joseph's Prep",
      "level": "HS",
      "stats_summary": "4 IP, 8 K, 0 ER",
      "game_context": "W 5-1",
      "game_status": "Final",
      "game_time": null,
      "game_date": "2026-04-01",
      "is_yesterday": true,
      "next_game": null,
      "box_score_url": null,
      "player_profile_url": null,
      "performance_grade": "🔥 Standout",
      "grade_reason": "Dominant — 8 K vs 1 BB with 0 ER",
      "social_search_url": "https://x.com/search?q=%22Chris%20Grasso%22%20St.%20Joseph%27s%20Prep&f=live",
      "data_source": "HS Sheet",
      "is_client": true,
      "tags": {
        "draft_class": "2027",
        "position": "Pitcher",
        "roster_priority": 2
      }
    },
    {
      "player_name": "Devin Diaz",
      "team": "Iona Prep",
      "level": "HS",
      "stats_summary": "1-4, 1 R",
      "game_context": "L 10-6",
      "game_status": "Final",
      "game_time": null,
      "game_date": "2026-04-01",
      "is_yesterday": true,
      "next_game": null,
      "box_score_url": null,
      "player_profile_url": null,
      "performance_grade": "😐 Routine",
      "grade_reason": "1-for-4",
      "social_search_url": "https://x.com/search?q=%22Devin%20Diaz%22%20Iona%20Prep&f=live",
      "data_source": "HS Sheet",
      "is_client": true,
      "tags": {
        "draft_class": "2026",
        "position": "Hitter",
        "roster_priority": 2
      }
    },
    {
      "player_name": "Will Myhand",
      "team": "Mill Creek",
      "level": "HS",
      "stats_summary": "1-2, 2 R, 1 BB",
      "game_context": "W 10-0",
      "game_status": "Final",
      "game_time": null,
      "game_date": "2026-04-01",
      "is_yesterday": true,
      "next_game": null,
      "box_score_url": null,
      "player_profile_url": null,
      "performance_grade": "✅ Good",
      "grade_reason": "Productive game",
      "social_search_url": "https://x.com/search?q=%22Will%20Myhand%22%20Mill%20Creek&f=live",
      "data_source": "HS Sheet",
      "is_client": true,
      "tags": {
        "draft_class": "2026",
        "position": "Hitter",
        "roster_priority": 4
      }
    },
    {
      "player_name": "Lucas Lawerence",
      "team": "HS",
      "level": "HS",
      "stats_summary": "1 IP, 0 K, 0 ER",
      "game_context": "",
      "game_status": "Final",
      "game_time": null,
      "game_date": "2026-04-01",
      "is_yesterday": true,
      "next_game": null,
      "box_score_url": null,
      "player_profile_url": null,
      "performance_grade": "✅ Good",
      "grade_reason": "Scoreless in 1 IP",
      "social_search_url": "https://x.com/search?q=%22Lucas%20Lawerence%22%20HS&f=live",
      "data_source": "HS Sheet",
      "is_client": false,
      "tags": {
        "draft_class": "",
        "position": "Pitcher",
        "roster_priority": 99
      }
    },
    {
      "player_name": "Axton Westmoreland",
      "team": "Hernando",
      "level": "HS",
      "stats_summary": "0-1, 2 R, 2 BB",
      "game_context": "W 17-3",
      "game_status": "Final",
      "game_time": null,
      "game_date": "2026-04-01",
      "is_yesterday": true,
      "next_game": null,
      "box_score_url": null,
      "player_profile_url": null,
      "performance_grade": "✅ Good",
      "grade_reason": "Productive game",
      "social_search_url": "https://x.com/search?q=%22Axton%20Westmoreland%22%20Hernando&f=live",
      "data_source": "HS Sheet",
      "is_client": true,
      "tags": {
        "draft_class": "2028",
        "position": "Hitter",
        "roster_priority": 2
      }
    }
  ]
}